injectpy/__init__.py
injectpy/kernel.py
injectpy/reflection.py
injectpy/utils.py
injectpy-0.0.1.dist-info/METADATA
injectpy-0.0.1.dist-info/WHEEL
injectpy-0.0.1.dist-info/top_level.txt
injectpy-0.0.1.dist-info/RECORD
